src/cache.py
src/client.py
src/config.py
src/constants.py
src/exceptions.py
src/formatting.py
src/main.py
src/models.py
src/rate_limiter.py
src/state.py
src/utils.py
src/validators.py
src/prompts/__init__.py
src/prompts/captain_recommendation.py
src/prompts/chips.py
src/prompts/league_analysis.py
src/prompts/player_analysis.py
src/prompts/squad_analysis.py
src/prompts/team_analysis.py
src/prompts/team_selection.py
src/prompts/transfers.py
src/resources/__init__.py
src/resources/bootstrap.py
src/tools/__init__.py
src/tools/fixtures.py
src/tools/gameweeks.py
src/tools/leagues.py
src/tools/players.py
src/tools/teams.py
src/tools/transfers.py
fpl_mcp_server-0.1.7.dist-info/METADATA
fpl_mcp_server-0.1.7.dist-info/WHEEL
fpl_mcp_server-0.1.7.dist-info/entry_points.txt
fpl_mcp_server-0.1.7.dist-info/licenses/LICENSE
fpl_mcp_server-0.1.7.dist-info/RECORD
