Metadata-Version: 2.4
Name: fpl-mcp-server
Version: 0.1.7
Summary: Fantasy Premier League MCP Server
Project-URL: Homepage, https://github.com/nguyenanhducs/fpl-mcp
Project-URL: Repository, https://github.com/nguyenanhducs/fpl-mcp
Project-URL: Issues, https://github.com/nguyenanhducs/fpl-mcp/issues
Project-URL: Documentation, https://github.com/nguyenanhducs/fpl-mcp#readme
Author: Anh Duc Nguyen
License-Expression: MIT
License-File: LICENSE
Keywords: fantasy-premier-league,fpl,mcp,model-context-protocol
Classifier: License :: OSI Approved :: MIT License
Classifier: Programming Language :: Python :: 3
Classifier: Programming Language :: Python :: 3.13
Classifier: Topic :: Games/Entertainment :: Simulation
Classifier: Topic :: Software Development :: Libraries :: Python Modules
Requires-Python: >=3.13
Requires-Dist: httpx>=0.28.0
Requires-Dist: mcp>=1.20.0
Requires-Dist: pydantic-settings>=2.12.0
Requires-Dist: pydantic>=2.12.0
Requires-Dist: python-dotenv>=1.0.0
Provides-Extra: dev
Requires-Dist: pytest-asyncio>=0.21.0; extra == 'dev'
Requires-Dist: pytest-cov>=4.0.0; extra == 'dev'
Requires-Dist: pytest-mock>=3.10.0; extra == 'dev'
Requires-Dist: pytest>=7.0.0; extra == 'dev'
Requires-Dist: ruff>=0.14.0; extra == 'dev'
